envotate/__init__.py
envotate/env.py
envotate/exceptions.py
envotate/py.typed
envotate/types.py
envotate/typing.py
tests/__init__.py
tests/conftest.py
tests/test_classes.py
tests/test_modules.py
tests/test_types.py
tests/testapp/__init__.py
tests/testapp/settings.py
envotate-0.0.1.dist-info/LICENSE
envotate-0.0.1.dist-info/METADATA
envotate-0.0.1.dist-info/WHEEL
envotate-0.0.1.dist-info/top_level.txt
envotate-0.0.1.dist-info/RECORD
