Metadata-Version: 2.1
Name: envotate
Version: 0.0.1
Summary: Settings management using environment variables and type annotations.
Home-page: https://github.com/jordaneremieff/envotate
Author: Jordan Eremieff
Author-email: jordan@eremieff.com
License: MIT
Platform: UNKNOWN
Classifier: License :: OSI Approved :: MIT License
Classifier: Operating System :: OS Independent
Classifier: Programming Language :: Python
Classifier: Programming Language :: Python :: 3
Classifier: Programming Language :: Python :: 3.9
Classifier: Programming Language :: Python :: 3.10
Requires-Python: >=3.9
